MANIFEST.in
readme.md
requirements.txt
setup.cfg
setup.py
JsonSimple/JsonSimple.py
JsonSimple/__init__.py
JsonSimple.egg-info/PKG-INFO
JsonSimple.egg-info/SOURCES.txt
JsonSimple.egg-info/dependency_links.txt
JsonSimple.egg-info/requires.txt
JsonSimple.egg-info/top_level.txt